{
	"name": "Conch Tour Train",
	"description": "<p><span class=\"arial-brown-13-extended\">As a legacy to Henry Flagler&rsquo;s &ldquo;railway over the sea&rdquo; the <a class=\"arial-brown-13-extended-invisible-link\" href=\"http://www.conchtourtrain.com/\" target=\"_blank\">Conch Tour Train</a> has treated visitors to an in-depth view of the city&rsquo;s most charming, historic and interesting attractions for 50 years...and counting. The Conch Tour Train took its inaugural ride in 1958 and has been offering tours throughout Key West ever since. &nbsp;For a historic adventure through Key West, take a ride on board Key West's original sightseeing tour, the Conch Tour Train.</span></p>",
	"url": "http://www.conchtourtrain.com/key-west-tickets.html",
	"about": "<p>As a legacy to Henry Flagler&rsquo;s &ldquo;railway over the sea&rdquo; the&nbsp;<a class=\"arial-brown-13-extended-invisible-link\" href=\"http://www.conchtourtrain.com/\" target=\"_blank\">Conch Tour Train</a>&nbsp;has treated visitors to an in-depth view of the city&rsquo;s most charming, historic and interesting attractions for 50 years...and counting. The Conch Tour Train took its inaugural ride in 1958 and has been offering tours throughout Key West ever since. &nbsp;For a historic adventure through Key West, take a ride on board Key West's original sightseeing tour, the Conch Tour Train.</p>",
	"sort_order": 8,
	"image": {
		"url": "https://cdn.traveltripper.io/site-assets/359_384_2170/media/2017-03-13-105726/conchtourtrain.jpg"
	},
	"detail_image": {
		"url": "https://cdn.traveltripper.io/site-assets/359_384_2170/media/2017-03-13-105726/conchtourtrain.jpg"
	}
}