{
	"name": "Shipwreck Musuem",
	"url": "https://www.keywestshipwreck.com/",
	"description": "<p>Enter the world of 1856 Key West&hellip; the era of the wreckers. At the Key West Shipwreck Museum you will step back into time as you discover Key West&rsquo;s unique maritime heritage and how it became the richest city in the United States.</p>",
	"about": "<p>Enter the world of 1856 Key West&hellip; the era of the wreckers. At the Key West Shipwreck Museum you will step back into time as you discover Key West&rsquo;s unique maritime heritage and how it became the richest city in the United States.</p>",
	"image": {
		"url": "https://cdn.traveltripper.io/site-assets/359_384_2170/media/2017-03-13-104746/shipwreckmuseum.jpg"
	},
	"detail_image": {
		"url": "https://cdn.traveltripper.io/site-assets/359_384_2170/media/2017-03-13-104746/shipwreckmuseum.jpg"
	},
	"sort_order": 8
}